viazoom-0.1.5.dist-info/METADATA
viazoom-0.1.5.dist-info/WHEEL
viazoom.libs/libssl-989c0fb4.so.1.1
viazoom.libs/libcrypto-f0ab144a.so.1.1
viazoom/__init__.py
viazoom/__init__.pyi
viazoom/py.typed
viazoom/viazoom.abi3.so
viazoom-0.1.5.dist-info/RECORD
